{
  "success": true,
  "source": "steam-news-api+steamdb-links",
  "generatedAt": "2026-04-28T22:14:12.874298+00:00",
  "totalGames": 39,
  "mappedGames": 39,
  "games": [
    {
      "game": "ARC Raiders",
      "appId": 1808500,
      "steamDbUrl": "https://steamdb.info/app/1808500/",
      "latestPatchTitle": null,
      "latestPatchUrl": null,
      "latestPatchPublishedAt": null,
      "status": "error",
      "error": "HTTP Error 502: Bad Gateway"
    },
    {
      "game": "ARK Survival Ascended",
      "appId": 2399830,
      "steamDbUrl": "https://steamdb.info/app/2399830/",
      "latestPatchTitle": null,
      "latestPatchUrl": null,
      "latestPatchPublishedAt": null,
      "status": "error",
      "error": "HTTP Error 502: Bad Gateway"
    },
    {
      "game": "ARK Survival Evolved",
      "appId": 346110,
      "steamDbUrl": "https://steamdb.info/app/346110/",
      "latestPatchTitle": null,
      "latestPatchUrl": null,
      "latestPatchPublishedAt": null,
      "status": "error",
      "error": "HTTP Error 502: Bad Gateway"
    },
    {
      "game": "Albion Online",
      "appId": 761890,
      "steamDbUrl": "https://steamdb.info/app/761890/",
      "latestPatchTitle": null,
      "latestPatchUrl": null,
      "latestPatchPublishedAt": null,
      "status": "error",
      "error": "HTTP Error 502: Bad Gateway"
    },
    {
      "game": "Apex Legends",
      "appId": 1172470,
      "steamDbUrl": "https://steamdb.info/app/1172470/",
      "latestPatchTitle": null,
      "latestPatchUrl": null,
      "latestPatchPublishedAt": null,
      "status": "error",
      "error": "HTTP Error 502: Bad Gateway"
    },
    {
      "game": "Arena Breakout",
      "appId": 2073620,
      "steamDbUrl": "https://steamdb.info/app/2073620/",
      "latestPatchTitle": null,
      "latestPatchUrl": null,
      "latestPatchPublishedAt": null,
      "status": "error",
      "error": "HTTP Error 502: Bad Gateway"
    },
    {
      "game": "Arena Breakout Infinite",
      "appId": 2073620,
      "steamDbUrl": "https://steamdb.info/app/2073620/",
      "latestPatchTitle": null,
      "latestPatchUrl": null,
      "latestPatchPublishedAt": null,
      "status": "error",
      "error": "HTTP Error 502: Bad Gateway"
    },
    {
      "game": "Arma 3",
      "appId": 107410,
      "steamDbUrl": "https://steamdb.info/app/107410/",
      "latestPatchTitle": null,
      "latestPatchUrl": null,
      "latestPatchPublishedAt": null,
      "status": "error",
      "error": "HTTP Error 502: Bad Gateway"
    },
    {
      "game": "Arma Reforger",
      "appId": 1874880,
      "steamDbUrl": "https://steamdb.info/app/1874880/",
      "latestPatchTitle": null,
      "latestPatchUrl": null,
      "latestPatchPublishedAt": null,
      "status": "error",
      "error": "HTTP Error 502: Bad Gateway"
    },
    {
      "game": "Battlebit",
      "appId": 671860,
      "steamDbUrl": "https://steamdb.info/app/671860/",
      "latestPatchTitle": null,
      "latestPatchUrl": null,
      "latestPatchPublishedAt": null,
      "status": "error",
      "error": "HTTP Error 502: Bad Gateway"
    },
    {
      "game": "Battlefield 6",
      "appId": 671860,
      "steamDbUrl": "https://steamdb.info/app/671860/",
      "latestPatchTitle": null,
      "latestPatchUrl": null,
      "latestPatchPublishedAt": null,
      "status": "error",
      "error": "HTTP Error 502: Bad Gateway"
    },
    {
      "game": "Beasts of Bermuda",
      "appId": 719890,
      "steamDbUrl": "https://steamdb.info/app/719890/",
      "latestPatchTitle": null,
      "latestPatchUrl": null,
      "latestPatchPublishedAt": null,
      "status": "error",
      "error": "HTTP Error 502: Bad Gateway"
    },
    {
      "game": "Call of Duty",
      "appId": 1938090,
      "steamDbUrl": "https://steamdb.info/app/1938090/",
      "latestPatchTitle": null,
      "latestPatchUrl": null,
      "latestPatchPublishedAt": null,
      "status": "error",
      "error": "HTTP Error 502: Bad Gateway"
    },
    {
      "game": "Conan Exiles",
      "appId": 440900,
      "steamDbUrl": "https://steamdb.info/app/440900/",
      "latestPatchTitle": null,
      "latestPatchUrl": null,
      "latestPatchPublishedAt": null,
      "status": "error",
      "error": "HTTP Error 502: Bad Gateway"
    },
    {
      "game": "Counter-Strike 2",
      "appId": 730,
      "steamDbUrl": "https://steamdb.info/app/730/",
      "latestPatchTitle": null,
      "latestPatchUrl": null,
      "latestPatchPublishedAt": null,
      "status": "error",
      "error": "HTTP Error 502: Bad Gateway"
    },
    {
      "game": "Dark and Darker",
      "appId": 2016590,
      "steamDbUrl": "https://steamdb.info/app/2016590/",
      "latestPatchTitle": null,
      "latestPatchUrl": null,
      "latestPatchPublishedAt": null,
      "status": "error",
      "error": "HTTP Error 502: Bad Gateway"
    },
    {
      "game": "DayZ",
      "appId": 221100,
      "steamDbUrl": "https://steamdb.info/app/221100/",
      "latestPatchTitle": null,
      "latestPatchUrl": null,
      "latestPatchPublishedAt": null,
      "status": "error",
      "error": "HTTP Error 502: Bad Gateway"
    },
    {
      "game": "Dead by Daylight",
      "appId": 381210,
      "steamDbUrl": "https://steamdb.info/app/381210/",
      "latestPatchTitle": null,
      "latestPatchUrl": null,
      "latestPatchPublishedAt": null,
      "status": "error",
      "error": "HTTP Error 502: Bad Gateway"
    },
    {
      "game": "Delta Force",
      "appId": 2507950,
      "steamDbUrl": "https://steamdb.info/app/2507950/",
      "latestPatchTitle": null,
      "latestPatchUrl": null,
      "latestPatchPublishedAt": null,
      "status": "error",
      "error": "HTTP Error 502: Bad Gateway"
    },
    {
      "game": "Dune Awakening",
      "appId": 1172710,
      "steamDbUrl": "https://steamdb.info/app/1172710/",
      "latestPatchTitle": null,
      "latestPatchUrl": null,
      "latestPatchPublishedAt": null,
      "status": "error",
      "error": "HTTP Error 502: Bad Gateway"
    },
    {
      "game": "Farlight 84",
      "appId": 1928420,
      "steamDbUrl": "https://steamdb.info/app/1928420/",
      "latestPatchTitle": null,
      "latestPatchUrl": null,
      "latestPatchPublishedAt": null,
      "status": "error",
      "error": "HTTP Error 502: Bad Gateway"
    },
    {
      "game": "Gray Zone Warfare",
      "appId": 2479810,
      "steamDbUrl": "https://steamdb.info/app/2479810/",
      "latestPatchTitle": null,
      "latestPatchUrl": null,
      "latestPatchPublishedAt": null,
      "status": "error",
      "error": "HTTP Error 502: Bad Gateway"
    },
    {
      "game": "Hell Let Loose",
      "appId": 686810,
      "steamDbUrl": "https://steamdb.info/app/686810/",
      "latestPatchTitle": null,
      "latestPatchUrl": null,
      "latestPatchPublishedAt": null,
      "status": "error",
      "error": "HTTP Error 502: Bad Gateway"
    },
    {
      "game": "Hunt: Showdown",
      "appId": 594650,
      "steamDbUrl": "https://steamdb.info/app/594650/",
      "latestPatchTitle": null,
      "latestPatchUrl": null,
      "latestPatchPublishedAt": null,
      "status": "error",
      "error": "HTTP Error 502: Bad Gateway"
    },
    {
      "game": "Marvel Rivals",
      "appId": 2767030,
      "steamDbUrl": "https://steamdb.info/app/2767030/",
      "latestPatchTitle": null,
      "latestPatchUrl": null,
      "latestPatchPublishedAt": null,
      "status": "error",
      "error": "HTTP Error 502: Bad Gateway"
    },
    {
      "game": "Naraka",
      "appId": 1203220,
      "steamDbUrl": "https://steamdb.info/app/1203220/",
      "latestPatchTitle": null,
      "latestPatchUrl": null,
      "latestPatchPublishedAt": null,
      "status": "error",
      "error": "HTTP Error 502: Bad Gateway"
    },
    {
      "game": "PUBG",
      "appId": 578080,
      "steamDbUrl": "https://steamdb.info/app/578080/",
      "latestPatchTitle": null,
      "latestPatchUrl": null,
      "latestPatchPublishedAt": null,
      "status": "error",
      "error": "HTTP Error 502: Bad Gateway"
    },
    {
      "game": "Palworld",
      "appId": 1623730,
      "steamDbUrl": "https://steamdb.info/app/1623730/",
      "latestPatchTitle": null,
      "latestPatchUrl": null,
      "latestPatchPublishedAt": null,
      "status": "error",
      "error": "HTTP Error 502: Bad Gateway"
    },
    {
      "game": "Rainbow Six Siege",
      "appId": 359550,
      "steamDbUrl": "https://steamdb.info/app/359550/",
      "latestPatchTitle": null,
      "latestPatchUrl": null,
      "latestPatchPublishedAt": null,
      "status": "error",
      "error": "HTTP Error 502: Bad Gateway"
    },
    {
      "game": "Rust",
      "appId": 252490,
      "steamDbUrl": "https://steamdb.info/app/252490/",
      "latestPatchTitle": null,
      "latestPatchUrl": null,
      "latestPatchPublishedAt": null,
      "status": "error",
      "error": "HTTP Error 502: Bad Gateway"
    },
    {
      "game": "SCUM",
      "appId": 513710,
      "steamDbUrl": "https://steamdb.info/app/513710/",
      "latestPatchTitle": null,
      "latestPatchUrl": null,
      "latestPatchPublishedAt": null,
      "status": "error",
      "error": "HTTP Error 502: Bad Gateway"
    },
    {
      "game": "SMITE 2",
      "appId": 2437170,
      "steamDbUrl": "https://steamdb.info/app/2437170/",
      "latestPatchTitle": null,
      "latestPatchUrl": null,
      "latestPatchPublishedAt": null,
      "status": "error",
      "error": "HTTP Error 502: Bad Gateway"
    },
    {
      "game": "STALCRAFT",
      "appId": 1818450,
      "steamDbUrl": "https://steamdb.info/app/1818450/",
      "latestPatchTitle": null,
      "latestPatchUrl": null,
      "latestPatchPublishedAt": null,
      "status": "error",
      "error": "HTTP Error 502: Bad Gateway"
    },
    {
      "game": "Sea of Thieves",
      "appId": 1172620,
      "steamDbUrl": "https://steamdb.info/app/1172620/",
      "latestPatchTitle": null,
      "latestPatchUrl": null,
      "latestPatchPublishedAt": null,
      "status": "error",
      "error": "HTTP Error 502: Bad Gateway"
    },
    {
      "game": "Squad",
      "appId": 393380,
      "steamDbUrl": "https://steamdb.info/app/393380/",
      "latestPatchTitle": null,
      "latestPatchUrl": null,
      "latestPatchPublishedAt": null,
      "status": "error",
      "error": "HTTP Error 502: Bad Gateway"
    },
    {
      "game": "The Finals",
      "appId": 2073850,
      "steamDbUrl": "https://steamdb.info/app/2073850/",
      "latestPatchTitle": null,
      "latestPatchUrl": null,
      "latestPatchPublishedAt": null,
      "status": "error",
      "error": "HTTP Error 502: Bad Gateway"
    },
    {
      "game": "The Isle Evrima",
      "appId": 376210,
      "steamDbUrl": "https://steamdb.info/app/376210/",
      "latestPatchTitle": null,
      "latestPatchUrl": null,
      "latestPatchPublishedAt": null,
      "status": "error",
      "error": "HTTP Error 502: Bad Gateway"
    },
    {
      "game": "Unturned",
      "appId": 304930,
      "steamDbUrl": "https://steamdb.info/app/304930/",
      "latestPatchTitle": null,
      "latestPatchUrl": null,
      "latestPatchPublishedAt": null,
      "status": "error",
      "error": "HTTP Error 502: Bad Gateway"
    },
    {
      "game": "WarThunder",
      "appId": 236390,
      "steamDbUrl": "https://steamdb.info/app/236390/",
      "latestPatchTitle": null,
      "latestPatchUrl": null,
      "latestPatchPublishedAt": null,
      "status": "error",
      "error": "HTTP Error 502: Bad Gateway"
    }
  ]
}
