{
  "success": true,
  "source": "steam-news-api+steamdb-links",
  "generatedAt": "2026-06-06T06:07:58.264180+00:00",
  "totalGames": 48,
  "mappedGames": 48,
  "games": [
    {
      "game": "ARC Raiders",
      "appId": 1808500,
      "steamDbUrl": "https://steamdb.info/app/1808500/",
      "latestPatchTitle": "Store Update 1.31.0",
      "latestPatchUrl": "https://steamstore-a.akamaihd.net/news/externalpost/steam_community_announcements/1833968530899786",
      "latestPatchPublishedAt": "2026-06-02T09:02:05+00:00",
      "status": "ok"
    },
    {
      "game": "ARK Survival Ascended",
      "appId": 2399830,
      "steamDbUrl": "https://steamdb.info/app/2399830/",
      "latestPatchTitle": "Community Crunch 510: Rise of the Tickle Chicken",
      "latestPatchUrl": "https://steamstore-a.akamaihd.net/news/externalpost/steam_community_announcements/1834602721192589",
      "latestPatchPublishedAt": "2026-06-06T00:01:06+00:00",
      "status": "ok"
    },
    {
      "game": "ARK Survival Evolved",
      "appId": 346110,
      "steamDbUrl": "https://steamdb.info/app/346110/",
      "latestPatchTitle": "ARK: Aquatica Official servers update",
      "latestPatchUrl": "https://steamstore-a.akamaihd.net/news/externalpost/steam_community_announcements/1821922921817276",
      "latestPatchPublishedAt": "2026-01-16T23:28:55+00:00",
      "status": "ok"
    },
    {
      "game": "Active Matter",
      "appId": 2887580,
      "steamDbUrl": "https://steamdb.info/app/2887580/",
      "latestPatchTitle": "New Overtime Raid: \"Headquarters: Assistance Protocol\"",
      "latestPatchUrl": "https://steamstore-a.akamaihd.net/news/externalpost/steam_community_announcements/1834602721186926",
      "latestPatchPublishedAt": "2026-06-04T09:04:43+00:00",
      "status": "ok"
    },
    {
      "game": "Albion Online",
      "appId": 761890,
      "steamDbUrl": "https://steamdb.info/app/761890/",
      "latestPatchTitle": "Ambassador Spotlight: TheRealUriel",
      "latestPatchUrl": "https://steamstore-a.akamaihd.net/news/externalpost/steam_community_announcements/1834602721187057",
      "latestPatchPublishedAt": "2026-06-04T10:00:44+00:00",
      "status": "ok"
    },
    {
      "game": "Apex Legends",
      "appId": 1172470,
      "steamDbUrl": "https://steamdb.info/app/1172470/",
      "latestPatchTitle": "Apex Legends: Latest Update 6/5/2026",
      "latestPatchUrl": "https://steamstore-a.akamaihd.net/news/externalpost/steam_community_announcements/1834602721191890",
      "latestPatchPublishedAt": "2026-06-05T20:08:50+00:00",
      "status": "ok"
    },
    {
      "game": "Arena Breakout",
      "appId": 2073620,
      "steamDbUrl": "https://steamdb.info/app/2073620/",
      "latestPatchTitle": "Arena Breakout: Infinite Bans Notice - June 3rd",
      "latestPatchUrl": "https://steamstore-a.akamaihd.net/news/externalpost/steam_community_announcements/1834602721185007",
      "latestPatchPublishedAt": "2026-06-03T14:43:30+00:00",
      "status": "ok"
    },
    {
      "game": "Arena Breakout Infinite",
      "appId": 2073620,
      "steamDbUrl": "https://steamdb.info/app/2073620/",
      "latestPatchTitle": "Arena Breakout: Infinite Bans Notice - June 3rd",
      "latestPatchUrl": "https://steamstore-a.akamaihd.net/news/externalpost/steam_community_announcements/1834602721185007",
      "latestPatchPublishedAt": "2026-06-03T14:43:30+00:00",
      "status": "ok"
    },
    {
      "game": "Arma 3",
      "appId": 107410,
      "steamDbUrl": "https://steamdb.info/app/107410/",
      "latestPatchTitle": "Community Radar #61",
      "latestPatchUrl": "https://steamstore-a.akamaihd.net/news/externalpost/steam_community_announcements/1833334318571830",
      "latestPatchPublishedAt": "2026-05-22T14:00:35+00:00",
      "status": "ok"
    },
    {
      "game": "Arma Reforger",
      "appId": 1874880,
      "steamDbUrl": "https://steamdb.info/app/1874880/",
      "latestPatchTitle": "Update 1.7",
      "latestPatchUrl": "https://steamstore-a.akamaihd.net/news/externalpost/steam_community_announcements/1833968530887771",
      "latestPatchPublishedAt": "2026-05-28T11:07:22+00:00",
      "status": "ok"
    },
    {
      "game": "Battlebit",
      "appId": 671860,
      "steamDbUrl": "https://steamdb.info/app/671860/",
      "latestPatchTitle": "Operation Overhaul Dev Blog #3: New maps",
      "latestPatchUrl": "https://steamstore-a.akamaihd.net/news/externalpost/steam_community_announcements/1833968530886017",
      "latestPatchPublishedAt": "2026-05-27T17:00:05+00:00",
      "status": "ok"
    },
    {
      "game": "Battlefield 6",
      "appId": 671860,
      "steamDbUrl": "https://steamdb.info/app/671860/",
      "latestPatchTitle": "Operation Overhaul Dev Blog #3: New maps",
      "latestPatchUrl": "https://steamstore-a.akamaihd.net/news/externalpost/steam_community_announcements/1833968530886017",
      "latestPatchPublishedAt": "2026-05-27T17:00:05+00:00",
      "status": "ok"
    },
    {
      "game": "Beasts of Bermuda",
      "appId": 719890,
      "steamDbUrl": "https://steamdb.info/app/719890/",
      "latestPatchTitle": "Character Migrations for Official Servers!",
      "latestPatchUrl": "https://steamstore-a.akamaihd.net/news/externalpost/steam_community_announcements/1833334318566434",
      "latestPatchPublishedAt": "2026-05-20T14:34:26+00:00",
      "status": "ok"
    },
    {
      "game": "Call of Duty",
      "appId": 1938090,
      "steamDbUrl": "https://steamdb.info/app/1938090/",
      "latestPatchTitle": "Call of Duty: Black Ops 7 and Warzone - Season 04 - Live",
      "latestPatchUrl": "https://steamstore-a.akamaihd.net/news/externalpost/steam_community_announcements/1834602721188157",
      "latestPatchPublishedAt": "2026-06-04T16:49:09+00:00",
      "status": "ok"
    },
    {
      "game": "Chess",
      "appId": 1349230,
      "steamDbUrl": "https://steamdb.info/app/1349230/",
      "latestPatchTitle": "Tiny Bugfix Update",
      "latestPatchUrl": "https://steamstore-a.akamaihd.net/news/externalpost/steam_community_announcements/4186652991107671279",
      "latestPatchPublishedAt": "2021-11-04T01:11:48+00:00",
      "status": "ok"
    },
    {
      "game": "Conan Exiles",
      "appId": 440900,
      "steamDbUrl": "https://steamdb.info/app/440900/",
      "latestPatchTitle": "June Hotfix 1.1.2",
      "latestPatchUrl": "https://steamstore-a.akamaihd.net/news/externalpost/steam_community_announcements/1833968530900590",
      "latestPatchPublishedAt": "2026-06-02T14:01:48+00:00",
      "status": "ok"
    },
    {
      "game": "Counter-Strike 2",
      "appId": 730,
      "steamDbUrl": "https://steamdb.info/app/730/",
      "latestPatchTitle": "Counter-Strike 2 Update",
      "latestPatchUrl": "https://steamstore-a.akamaihd.net/news/externalpost/steam_community_announcements/1833968530889736",
      "latestPatchPublishedAt": "2026-05-29T00:17:23+00:00",
      "status": "ok"
    },
    {
      "game": "Dark and Darker",
      "appId": 2016590,
      "steamDbUrl": "https://steamdb.info/app/2016590/",
      "latestPatchTitle": "Streamer Invitational Event Match Grand Finals Result",
      "latestPatchUrl": "https://steamstore-a.akamaihd.net/news/externalpost/steam_community_announcements/1833968530896535",
      "latestPatchPublishedAt": "2026-06-01T05:43:39+00:00",
      "status": "ok"
    },
    {
      "game": "DayZ",
      "appId": 221100,
      "steamDbUrl": "https://steamdb.info/app/221100/",
      "latestPatchTitle": "DayZ Badlands | Dev Blog (Week 70) | Wishlist now!",
      "latestPatchUrl": "https://steamstore-a.akamaihd.net/news/externalpost/steam_community_announcements/1834602721190197",
      "latestPatchPublishedAt": "2026-06-05T10:31:08+00:00",
      "status": "ok"
    },
    {
      "game": "Dead by Daylight",
      "appId": 381210,
      "steamDbUrl": "https://steamdb.info/app/381210/",
      "latestPatchTitle": "At long last, Dead by Daylight welcomes Friday the 13th's Jason Voorhees, and he's now available for some beta slashing",
      "latestPatchUrl": "https://steamstore-a.akamaihd.net/news/externalpost/Rock, Paper, Shotgun/1833334318579881",
      "latestPatchPublishedAt": "2026-05-26T16:09:18+00:00",
      "status": "ok"
    },
    {
      "game": "Deadside",
      "appId": 895400,
      "steamDbUrl": "https://steamdb.info/app/895400/",
      "latestPatchTitle": "Patch 1.9.3: PvE Server Changes & Bug Fixes",
      "latestPatchUrl": "https://steamstore-a.akamaihd.net/news/externalpost/steam_community_announcements/1833968530897902",
      "latestPatchPublishedAt": "2026-06-01T15:23:08+00:00",
      "status": "ok"
    },
    {
      "game": "Delta Force",
      "appId": 2507950,
      "steamDbUrl": "https://steamdb.info/app/2507950/",
      "latestPatchTitle": "G.T.I. Security | Operation Sentinel",
      "latestPatchUrl": "https://steamstore-a.akamaihd.net/news/externalpost/steam_community_announcements/1834602721189871",
      "latestPatchPublishedAt": "2026-06-05T08:38:16+00:00",
      "status": "ok"
    },
    {
      "game": "Dune Awakening",
      "appId": 1172710,
      "steamDbUrl": "https://steamdb.info/app/1172710/",
      "latestPatchTitle": "Communinet Signal #17",
      "latestPatchUrl": "https://steamstore-a.akamaihd.net/news/externalpost/steam_community_announcements/1834602721191205",
      "latestPatchPublishedAt": "2026-06-05T15:29:09+00:00",
      "status": "ok"
    },
    {
      "game": "EFT",
      "appId": 1144300,
      "steamDbUrl": "https://steamdb.info/app/1144300/",
      "latestPatchTitle": "Bokuten – Why I Became an Angel is 60% OFF for One Week!",
      "latestPatchUrl": "https://steamstore-a.akamaihd.net/news/externalpost/steam_community_announcements/1823191198612039",
      "latestPatchPublishedAt": "2026-02-02T18:11:22+00:00",
      "status": "ok"
    },
    {
      "game": "Escape From Tarkov",
      "appId": 3932890,
      "steamDbUrl": "https://steamdb.info/app/3932890/",
      "latestPatchTitle": "Streamer Challenge has begun!",
      "latestPatchUrl": "https://steamstore-a.akamaihd.net/news/externalpost/steam_community_announcements/1834602721185060",
      "latestPatchPublishedAt": "2026-06-03T15:01:53+00:00",
      "status": "ok"
    },
    {
      "game": "Farlight 84",
      "appId": 1928420,
      "steamDbUrl": "https://steamdb.info/app/1928420/",
      "latestPatchTitle": "Farlight 84 New Season Update: \"Shadow Academy\"",
      "latestPatchUrl": "https://steamstore-a.akamaihd.net/news/externalpost/steam_community_announcements/1830797770232064",
      "latestPatchPublishedAt": "2026-04-23T02:37:13+00:00",
      "status": "ok"
    },
    {
      "game": "FragPunk",
      "appId": 2943650,
      "steamDbUrl": "https://steamdb.info/app/2943650/",
      "latestPatchTitle": "FragPunk June 3rd Patch Note",
      "latestPatchUrl": "https://steamstore-a.akamaihd.net/news/externalpost/steam_community_announcements/1834602721184472",
      "latestPatchPublishedAt": "2026-06-03T10:52:00+00:00",
      "status": "ok"
    },
    {
      "game": "Gray Zone Warfare",
      "appId": 2479810,
      "steamDbUrl": "https://steamdb.info/app/2479810/",
      "latestPatchTitle": "Patch 0.4.4.0 Now Live - Changelog",
      "latestPatchUrl": "https://steamstore-a.akamaihd.net/news/externalpost/steam_community_announcements/1834602721186918",
      "latestPatchPublishedAt": "2026-06-04T09:01:37+00:00",
      "status": "ok"
    },
    {
      "game": "Hell Let Loose",
      "appId": 686810,
      "steamDbUrl": "https://steamdb.info/app/686810/",
      "latestPatchTitle": "Update 20 | DX12 & WinStore",
      "latestPatchUrl": "https://steamstore-a.akamaihd.net/news/externalpost/steam_community_announcements/1834602721187908",
      "latestPatchPublishedAt": "2026-06-04T15:35:43+00:00",
      "status": "ok"
    },
    {
      "game": "Hunt: Showdown",
      "appId": 594650,
      "steamDbUrl": "https://steamdb.info/app/594650/",
      "latestPatchTitle": "Road to Hell - Roadmap",
      "latestPatchUrl": "https://steamstore-a.akamaihd.net/news/externalpost/steam_community_announcements/1834602721185683",
      "latestPatchPublishedAt": "2026-06-03T18:56:15+00:00",
      "status": "ok"
    },
    {
      "game": "Marathon",
      "appId": 3065800,
      "steamDbUrl": "https://steamdb.info/app/3065800/",
      "latestPatchTitle": "Marathon Open Play Week and Progression Update",
      "latestPatchUrl": "https://steamstore-a.akamaihd.net/news/externalpost/steam_community_announcements/1834602721192590",
      "latestPatchPublishedAt": "2026-06-06T00:01:24+00:00",
      "status": "ok"
    },
    {
      "game": "Marvel Rivals",
      "appId": 2767030,
      "steamDbUrl": "https://steamdb.info/app/2767030/",
      "latestPatchTitle": "Marvel Rivals Version 20260604 Patch Notes",
      "latestPatchUrl": "https://steamstore-a.akamaihd.net/news/externalpost/steam_community_announcements/1834602721186662",
      "latestPatchPublishedAt": "2026-06-04T06:25:15+00:00",
      "status": "ok"
    },
    {
      "game": "Naraka",
      "appId": 1203220,
      "steamDbUrl": "https://steamdb.info/app/1203220/",
      "latestPatchTitle": "NARAKA: BLADEPOINT Update – June 5th, 2026",
      "latestPatchUrl": "https://steamstore-a.akamaihd.net/news/externalpost/steam_community_announcements/1834602721184673",
      "latestPatchPublishedAt": "2026-06-03T12:18:49+00:00",
      "status": "ok"
    },
    {
      "game": "Off The Grid",
      "appId": 3659280,
      "steamDbUrl": "https://steamdb.info/app/3659280/",
      "latestPatchTitle": "The Gunslinger Content Pack",
      "latestPatchUrl": "https://steamstore-a.akamaihd.net/news/externalpost/steam_community_announcements/1832065502824090",
      "latestPatchPublishedAt": "2026-05-12T14:50:23+00:00",
      "status": "ok"
    },
    {
      "game": "PIONER",
      "appId": 3105890,
      "steamDbUrl": "https://steamdb.info/app/3105890/",
      "latestPatchTitle": "Take a look at a weapon from one of the upcoming updates",
      "latestPatchUrl": "https://steamstore-a.akamaihd.net/news/externalpost/steam_community_announcements/1833968530893397",
      "latestPatchPublishedAt": "2026-05-30T12:06:13+00:00",
      "status": "ok"
    },
    {
      "game": "PUBG",
      "appId": 578080,
      "steamDbUrl": "https://steamdb.info/app/578080/",
      "latestPatchTitle": "PUBG Global Series 6 Final Stage Day 3",
      "latestPatchUrl": "https://steamstore-a.akamaihd.net/news/externalpost/steam_community_announcements/1834602721191289",
      "latestPatchPublishedAt": "2026-06-05T16:00:17+00:00",
      "status": "ok"
    },
    {
      "game": "Palworld",
      "appId": 1623730,
      "steamDbUrl": "https://steamdb.info/app/1623730/",
      "latestPatchTitle": "Palworld 1.0 - July 10! Cinematic Trailer Reveal!",
      "latestPatchUrl": "https://steamstore-a.akamaihd.net/news/externalpost/steam_community_announcements/1834602721192331",
      "latestPatchPublishedAt": "2026-06-05T22:42:36+00:00",
      "status": "ok"
    },
    {
      "game": "Rainbow Six Siege",
      "appId": 359550,
      "steamDbUrl": "https://steamdb.info/app/359550/",
      "latestPatchTitle": "OPERATION SYSTEM OVERRIDE BEGINS NOW",
      "latestPatchUrl": "https://steamstore-a.akamaihd.net/news/externalpost/steam_community_announcements/1833968530900733",
      "latestPatchPublishedAt": "2026-06-02T15:00:14+00:00",
      "status": "ok"
    },
    {
      "game": "Rust",
      "appId": 252490,
      "steamDbUrl": "https://steamdb.info/app/252490/",
      "latestPatchTitle": "Rust is having a Face Off moment with its new update, introducing new and improved character models",
      "latestPatchUrl": "https://steamstore-a.akamaihd.net/news/externalpost/PCGamesN/1834602721191253",
      "latestPatchPublishedAt": "2026-06-05T15:28:05+00:00",
      "status": "ok"
    },
    {
      "game": "SCUM",
      "appId": 513710,
      "steamDbUrl": "https://steamdb.info/app/513710/",
      "latestPatchTitle": "SCUM - Community showcase",
      "latestPatchUrl": "https://steamstore-a.akamaihd.net/news/externalpost/steam_community_announcements/1833968530900378",
      "latestPatchPublishedAt": "2026-06-02T13:03:30+00:00",
      "status": "ok"
    },
    {
      "game": "SMITE 2",
      "appId": 2437170,
      "steamDbUrl": "https://steamdb.info/app/2437170/",
      "latestPatchTitle": "Horus Ascends! Take Flight in Update 36",
      "latestPatchUrl": "https://steamstore-a.akamaihd.net/news/externalpost/steam_community_announcements/1833968530898778",
      "latestPatchPublishedAt": "2026-06-01T21:13:35+00:00",
      "status": "ok"
    },
    {
      "game": "STALCRAFT",
      "appId": 1818450,
      "steamDbUrl": "https://steamdb.info/app/1818450/",
      "latestPatchTitle": "What lies ahead?",
      "latestPatchUrl": "https://steamstore-a.akamaihd.net/news/externalpost/steam_community_announcements/1834602721189913",
      "latestPatchPublishedAt": "2026-06-05T09:00:00+00:00",
      "status": "ok"
    },
    {
      "game": "Sea of Thieves",
      "appId": 1172620,
      "steamDbUrl": "https://steamdb.info/app/1172620/",
      "latestPatchTitle": "This Month in Sea of Thieves: June 2026",
      "latestPatchUrl": "https://steamstore-a.akamaihd.net/news/externalpost/steam_community_announcements/1834602721191812",
      "latestPatchPublishedAt": "2026-06-05T19:30:48+00:00",
      "status": "ok"
    },
    {
      "game": "Squad",
      "appId": 393380,
      "steamDbUrl": "https://steamdb.info/app/393380/",
      "latestPatchTitle": "Squad Status Update - May 2026 - Roadmap Showcase",
      "latestPatchUrl": "https://steamstore-a.akamaihd.net/news/externalpost/steam_community_announcements/1833968530891733",
      "latestPatchPublishedAt": "2026-05-29T16:53:08+00:00",
      "status": "ok"
    },
    {
      "game": "The Finals",
      "appId": 2073850,
      "steamDbUrl": "https://steamdb.info/app/2073850/",
      "latestPatchTitle": "Store Update 10.10.0",
      "latestPatchUrl": "https://steamstore-a.akamaihd.net/news/externalpost/steam_community_announcements/1834602721187056",
      "latestPatchPublishedAt": "2026-06-04T10:00:30+00:00",
      "status": "ok"
    },
    {
      "game": "The Isle Evrima",
      "appId": 376210,
      "steamDbUrl": "https://steamdb.info/app/376210/",
      "latestPatchTitle": "DevBlog #69",
      "latestPatchUrl": "https://steamstore-a.akamaihd.net/news/externalpost/steam_community_announcements/1833968530892663",
      "latestPatchPublishedAt": "2026-05-30T01:25:54+00:00",
      "status": "ok"
    },
    {
      "game": "Unturned",
      "appId": 304930,
      "steamDbUrl": "https://steamdb.info/app/304930/",
      "latestPatchTitle": "3.26.3.2 Patch Notes",
      "latestPatchUrl": "https://steamstore-a.akamaihd.net/news/externalpost/steam_community_announcements/1832065502813383",
      "latestPatchPublishedAt": "2026-05-07T21:00:56+00:00",
      "status": "ok"
    },
    {
      "game": "WarThunder",
      "appId": 236390,
      "steamDbUrl": "https://steamdb.info/app/236390/",
      "latestPatchTitle": "Screenshot Competition – Light and Lethal!",
      "latestPatchUrl": "https://steamstore-a.akamaihd.net/news/externalpost/steam_community_announcements/1834602721192910",
      "latestPatchPublishedAt": "2026-06-06T03:10:39+00:00",
      "status": "ok"
    }
  ]
}
